{
  "progress": 0.9,
  "stage": "fill_views_start",
  "current_work": "去重處理...",
  "log_messages": [
    "🚀 爬蟲任務已啟動...",
    "[05:26:02] 🔧 初始化爬蟲環境...",
    "[05:26:02] 🔐 讀取認證檔案...",
    "[05:26:03] ✅ 認證檔案讀取成功，包含 15 個 cookies",
    "[05:26:03] 📋 構建API請求參數...",
    "[05:26:03] 📊 目標用戶: @netflixtw",
    "[05:26:03] 📝 目標貼文數: 35",
    "[05:26:03] 🔄 爬取模式: 增量模式",
    "[05:26:03] 🧹 去重功能: 關閉",
    "[05:26:03] 🚀 發送API請求到Playwright Agent...",
    "[05:26:04] ⏳ 等待Playwright處理...",
    "[05:26:04] 📊 啟動瀏覽器...",
    "[05:26:12] 📊 導航到用戶頁面...",
    "[05:26:20] 📊 等待頁面加載...",
    "[05:26:28] 📊 開始智能滾動...",
    "[05:26:36] 📊 收集貼文URLs...",
    "[05:26:44] 📊 處理貼文URLs...",
    "[05:26:52] 📊 開始補齊詳細數據...",
    "[05:27:00] 📊 補齊貼文內容和互動數據...",
    "[05:27:08] 📊 開始補齊觀看數...",
    "[05:27:16] 📊 補齊觀看數據...",
    "[05:27:24] 📊 去重處理..."
  ],
  "start_time": 1754515562.837682,
  "username": "netflixtw",
  "timestamp": 1754515562.8403096
}